{
  "verse": {
    "id": 17,
    "chapter_id": 4,
    "verse_number": "1.11",
    "content_sanskrit": "कीकसायां यातुधाना विनतायां तु पक्षिणः । महावीर्याः सुता आसन् कश्यपस्य महात्मनः",
    "padaccheda": "कीकसायाम् - यातुधानाः - विनतायाम् - तु - पक्षिणः ।\nमहावीर्याः - सुताः - आसन् - कश्यपस्य - महात्मनः ॥",
    "anvaya": "महात्मनः कश्यपस्य कीकसायाम् यातुधानाः सुताः आसन् । विनतायाम् तु महावीर्याः पक्षिणः सुताः आसन् ।",
    "meaning_sanskrit": "",
    "meaning_english": "",
    "audio_url": null,
    "display_order": 11
  },
  "commentaries": [
    {
      "id": 1782919511952,
      "verse_id": 17,
      "commentary_type": "अन्वयार्थः",
      "author": "",
      "content": "{\"type\":\"word_meanings\",\"rows\":[[\"महात्मनः\",\"ದೊಡ್ಡದಾದ ಬುದ್ಧಿಯುಳ್ಳ\"],[\"कश्यपस्य\",\"ಕಶ್ಯಪ ಮಹರ್ಷಿಗಳಿಗೆ\"],[\"कीकसायाम्\",\"ಕೀಕಸಾದೇವಿಯವರಲ್ಲಿ\"],[\"यातुधानाः\",\"ರಾಕ್ಷಸರು\"],[\"सुताः\",\"ಮಕ್ಕಳು\"],[\"आसन्\",\"ಹುಟ್ಟಿದರು\"],[\"विनतायाम् तु\",\"ವಿನತಾದೇವಿಯವರಲ್ಲಾದರೂ\"],[\"महावीर्याः\",\"ಅಧಿಕವಾದ ಪರಾಕ್ರಮವುಳ್ಳ\"],[\"पक्षिणः\",\"ಗರುಡಾದಿ ಪಕ್ಷಿಗಳು\"],[\"सुताः\",\"ಮಕ್ಕಳು\"],[\"आसन्\",\"ಹುಟ್ಟಿದರು\"]]}"
    },
    {
      "id": 1782919511953,
      "verse_id": 17,
      "commentary_type": "शब्दः",
      "author": "",
      "content": "{\"type\":\"shabda_analysis\",\"headers\":[\"पदम्\",\"शब्दः\",\"अन्तः\",\"लिङ्गम्\",\"विभक्तिः\",\"वचनम्\"],\"rows\":[[\"महात्मनः\",\"महात्मन्\",\"नकारान्तः\",\"पुंलिङ्गः\",\"षष्ठीविभक्तिः\",\"एकवचनम्\"],[\"कश्यपस्य\",\"कश्यप\",\"अकारान्तः\",\"पुंलिङ्गः\",\"षष्ठीविभक्तिः\",\"एकवचनम्\"],[\"कीकसायाम्\",\"कीकसा\",\"आकारान्तः\",\"स्त्रीलिङ्गः\",\"सप्तमीविभक्तिः\",\"एकवचनम्\"],[\"यातुधानाः\",\"यातुधान\",\"अकारान्तः\",\"पुंलिङ्गः\",\"प्रथमाविभक्तिः\",\"बहुवचनम्\"],[\"सुताः\",\"सुत\",\"अकारान्तः\",\"पुंलिङ्गः\",\"प्रथमाविभक्तिः\",\"बहुवचनम्\"],[\"विनतायाम्\",\"विनता\",\"आकारान्तः\",\"स्त्रीलिङ्गः\",\"सप्तमीविभक्तिः\",\"एकवचनम्\"],[\"तु\",\"—\",\"—\",\"अव्ययम्\",\"—\",\"—\"],[\"महावीर्याः\",\"महावीर्य\",\"अकारान्तः\",\"पुंलिङ्गः\",\"प्रथमाविभक्तिः\",\"बहुवचनम्\"],[\"पक्षिणः\",\"पक्षिन्\",\"नकारान्तः\",\"पुंलिङ्गः\",\"प्रथमाविभक्तिः\",\"बहुवचनम्\"]]}"
    },
    {
      "id": 1782919511954,
      "verse_id": 17,
      "commentary_type": "समासः",
      "author": "",
      "content": "{\"type\":\"samasa\",\"headers\":[\"समासपदम्\",\"अवयवाः\",\"समासप्रकारः\"],\"rows\":[[\"महात्मनः\",\"महान् आत्मा यस्य सः महात्मा, तस्य\",\"बहुव्रीहिसमासः\"],[\"महावीर्याः\",\"महत् वीर्यं येषां ते महावीर्याः\",\"बहुव्रीहिसमासः\"]]}"
    },
    {
      "id": 1782919511955,
      "verse_id": 17,
      "commentary_type": "सन्धिः",
      "author": "",
      "content": "{\"type\":\"sandhi\",\"headers\":[\"सन्धिपदम्\",\"शब्दौ\",\"सन्धिप्रकारः\"],\"rows\":[[\"विनतायां तु\",\"विनतायाम् + तु\",\"अनुस्वारसन्धिः\"],[\"पक्षिणो महावीर्याः\",\"पक्षिणः + महावीर्याः\",\"विसर्गसन्धिः (उत्वम्)\"],[\"सुता आसन्\",\"सुताः + आसन्\",\"विसर्गसन्धिः (सकारः)\"]]}"
    },
    {
      "id": 1782919511956,
      "verse_id": 17,
      "commentary_type": "धातुः",
      "author": "",
      "content": "{\"type\":\"dhatu\",\"dhatus\":[{\"header\":\"अस भुवि (परस्मैपदी, अदादिगणः)\",\"tables\":[{\"lakara\":\"लट् लकारः (वर्तमानकालः)\",\"rows\":[[\"अस्ति\",\"स्तः\",\"सन्ति\",\"प्र०\"],[\"असि\",\"स्थः\",\"स्थ\",\"म०\"],[\"अस्मि\",\"स्वः\",\"स्मः\",\"उ०\"]]},{\"lakara\":\"लिट् लकारः (परोक्षभूतः)\",\"rows\":[[\"आस\",\"आसतुः\",\"आसुः\",\"प्र०\"],[\"आसिथ\",\"आसथुः\",\"आस\",\"म०\"],[\"आस\",\"आसिव\",\"आसिम\",\"उ०\"]]},{\"lakara\":\"लुट् लकारः (अनद्यतनभविष्यत्)\",\"rows\":[[\"भविता\",\"भवितारौ\",\"भवितारः\",\"प्र०\"],[\"भवितासि\",\"भवितास्थः\",\"भवितास्थ\",\"म०\"],[\"भवितास्मि\",\"भवितास्वः\",\"भवितास्मः\",\"उ०\"]]},{\"lakara\":\"लृट् लकारः (भविष्यत्)\",\"rows\":[[\"भविष्यति\",\"भविष्यतः\",\"भविष्यन्ति\",\"प्र०\"],[\"भविष्यसि\",\"भविष्यथः\",\"भविष्यथ\",\"म०\"],[\"भविष्यामि\",\"भविष्यावः\",\"भविष्यामः\",\"उ०\"]]},{\"lakara\":\"लोट् लकारः (आज्ञार्थः)\",\"rows\":[[\"अस्तु\",\"स्ताम्\",\"सन्तु\",\"प्र०\"],[\"एधि\",\"स्तम्\",\"स्त\",\"म०\"],[\"असानि\",\"असाव\",\"असाम\",\"उ०\"]]},{\"lakara\":\"लङ् लकारः (अनद्यतनभूतः)\",\"rows\":[[\"आसीत्\",\"आस्ताम्\",\"आसन्\",\"प्र०\"],[\"आसीः\",\"आस्तम्\",\"आस्त\",\"म०\"],[\"आसम्\",\"आस्व\",\"आस्म\",\"उ०\"]]},{\"lakara\":\"विधिलिङ् लकारः (विध्यर्थः)\",\"rows\":[[\"स्यात्\",\"स्याताम्\",\"स्युः\",\"प्र०\"],[\"स्याः\",\"स्यातम्\",\"स्यात\",\"म०\"],[\"स्याम्\",\"स्याव\",\"स्याम\",\"उ०\"]]},{\"lakara\":\"आशीर्लिङ् लकारः (आशीर्वादार्थः)\",\"rows\":[[\"भूयात्\",\"भूयास्ताम्\",\"भूयासुः\",\"प्र०\"],[\"भूयाः\",\"भूयास्तम्\",\"भूयास्त\",\"म०\"],[\"भूयासम्\",\"भूयास्व\",\"भूयास्म\",\"उ०\"]]},{\"lakara\":\"लुङ् लकारः (सामान्यभूतः)\",\"rows\":[[\"अभूत्\",\"अभूताम्\",\"अभूवन्\",\"प्र०\"],[\"अभूः\",\"अभूतम्\",\"अभूत\",\"म०\"],[\"अभूवम्\",\"अभूव\",\"अभूम\",\"उ०\"]]},{\"lakara\":\"लृङ् लकारः (क्रियातिपत्तिः)\",\"rows\":[[\"अभविष्यत्\",\"अभविष्यताम्\",\"अभविष्यन्\",\"प्र०\"],[\"अभविष्यः\",\"अभविष्यतम्\",\"अभविष्यत\",\"म०\"],[\"अभविष्यम्\",\"अभविष्याव\",\"अभविष्याम\",\"उ०\"]]}]}]}"
    },
    {
      "id": 1782919511957,
      "verse_id": 17,
      "commentary_type": "तात्पर्यम्",
      "author": "",
      "content": "महात्मनः कश्यपस्य कीकसायाम् यातुधानाः (राक्षसाः) उत्पन्नाः । विनतायाम् तु महावीर्याः पक्षिणः (गरुडादयः) सुताः आसन् ।"
    },
    {
      "id": 1782919511958,
      "verse_id": 17,
      "commentary_type": "विशेषांशः",
      "author": "",
      "content": "—"
    },
    {
      "id": 1782919511959,
      "verse_id": 17,
      "commentary_type": "आकांक्षा",
      "author": "",
      "content": "'आसन्' इत्यस्य के? → 'सुताः' (प्रथमा)\n'सुताः' कस्य? → 'कश्यपस्य' (षष्ठी)\n'कीकसायाम्' के सुताः आसन्? → 'यातुधानाः' (प्रथमा)\n'विनतायाम्' तु के सुताः आसन्? → 'पक्षिणः' (प्रथमा)\n'पक्षिणः' कीदृशाः? → 'महावीर्याः' (प्रथमा)"
    },
    {
      "id": 1782919511960,
      "verse_id": 17,
      "commentary_type": "संस्कृत व्याख्यानम्",
      "author": "",
      "content": "कीकसायामिति ।। महान् आत्मा बुद्धिर्यस्य तस्य कश्यपस्य कीकसायां यातुधानाः राक्षसाः । विनतायां तु महत् वीर्य पराक्रमोयेषांते पक्षिणो गरुडादि शकुन्ताः सुता आसन् ।"
    },
    {
      "id": 1782919511961,
      "verse_id": 17,
      "commentary_type": "श्रीमच्छलारि गूडप्रकाशिका",
      "author": "",
      "content": "कीकसायामिति ।। यातुधानाः यातनाः यातूनाः धीयन्ते येषु ते । यातुधानःपुण्यजनिति । पुण्यजनो विपरीत लक्षणयेति अमरटीका । पक्षिणः गरुडादयः ।। ११ ।।"
    }
  ]
}